qlinks/__init__.py
qlinks/exceptions/__init__.py
qlinks/lattice/__init__.py
qlinks/lattice/component.py
qlinks/lattice/spin_object.py
qlinks/lattice/square_lattice.py
qlinks/model.py
qlinks/solver/__init__.py
qlinks/solver/deep_first_search.py
qlinks/symmetry/__init__.py
qlinks/symmetry/abstract.py
qlinks/symmetry/computation_basis.py
qlinks/symmetry/gauss_law.py
qlinks/symmetry/global_flux.py
qlinks/symmetry/translation.py
qlinks/visualizer/__init__.py
qlinks/visualizer/graph.py
qlinks/visualizer/quiver.py
qlinks-0.1.0rc1.dist-info/LICENSE
qlinks-0.1.0rc1.dist-info/WHEEL
qlinks-0.1.0rc1.dist-info/METADATA
qlinks-0.1.0rc1.dist-info/RECORD
