Metadata-Version: 2.1
Name: qlinks
Version: 0.1.0rc1
Summary: Quantum link model
License: MIT
Author: Tan Tao-Lin
Author-email: tanlin2013@gmail.com
Requires-Python: >=3.8,<3.12
Classifier: License :: OSI Approved :: MIT License
Classifier: Programming Language :: Python :: 3
Classifier: Programming Language :: Python :: 3.8
Classifier: Programming Language :: Python :: 3.9
Classifier: Programming Language :: Python :: 3.10
Classifier: Programming Language :: Python :: 3.11
Provides-Extra: drawing
Requires-Dist: matplotlib (>=3.6.3,<4.0.0) ; extra == "drawing"
Requires-Dist: networkx (>=3.0,<4.0)
Requires-Dist: numpy (>=1.22,<2.0)
Requires-Dist: pulp (>=2.7.0,<3.0.0)
Requires-Dist: scipy (>=1.10.0,<2.0.0)
Requires-Dist: tqdm (>=4.63.0,<5.0.0)
